cloudkitect/patterns/__init__.py
cloudkitect/patterns/py.typed
cloudkitect/patterns/_jsii/__init__.py
cloudkitect/patterns/_jsii/patterns@1.4.1.jsii.tgz
cloudkitect.patterns-1.4.1.dist-info/LICENSE
cloudkitect.patterns-1.4.1.dist-info/METADATA
cloudkitect.patterns-1.4.1.dist-info/WHEEL
cloudkitect.patterns-1.4.1.dist-info/top_level.txt
cloudkitect.patterns-1.4.1.dist-info/RECORD
