Metadata-Version: 2.1
Name: cloudkitect.patterns
Version: 1.4.1
Summary: CloudKitect freemium patterns are built on top of CloudKitect freemium components which comply to various standards. Using these patterns you can host your website, or run your containerized app using ECS Fargate within a couple hours
Home-page: https://github.com/cloudkitect/freemium
Author: CloudKitect Inc<support@cloudkitect.com>
License: Apache-2.0
Project-URL: Source, https://github.com/cloudkitect/freemium
Classifier: Intended Audience :: Developers
Classifier: Operating System :: OS Independent
Classifier: Programming Language :: JavaScript
Classifier: Programming Language :: Python :: 3 :: Only
Classifier: Programming Language :: Python :: 3.8
Classifier: Programming Language :: Python :: 3.9
Classifier: Programming Language :: Python :: 3.10
Classifier: Programming Language :: Python :: 3.11
Classifier: Typing :: Typed
Classifier: Development Status :: 5 - Production/Stable
Classifier: License :: OSI Approved
Requires-Python: ~=3.8
License-File: LICENSE
Requires-Dist: aws-cdk-lib <3.0.0,>=2.137.0
Requires-Dist: cloudkitect.components <2.0.0,>=1.4.0
Requires-Dist: constructs <11.0.0,>=10.3.0
Requires-Dist: jsii <2.0.0,>=1.97.0
Requires-Dist: publication >=0.0.3
Requires-Dist: typeguard ~=2.13.3
